[
  {
    "timestamp": "2026-06-24 15:03:27",
    "output_file": "outputVideos/ego_hold_decy_085.mp4",
    "lanenet_model": "trained_models/LaneNetNew.pth",
    "lanenet_arch": "ENet",
    "hnet_model": "trained_models/hnet_best.pth",
    "video_file": "/Users/amannindra/Projects/Autonomous-Bicycle/HybridNets/demo/video/1.mp4",
    "width": 512,
    "height": 256,
    "embedding_activation": "raw",
    "hnet_poly_order": 3,
    "hnet_curve_thickness": 4,
    "delta_v": 0.5,
    "min_cluster_size": 50,
    "max_lanes": 3,
    "ego_alpha": 0.25,
    "ego_max_delta": 0.35,
    "ego_hold_decay": 0.85,
    "max_frames": 0
  },
  {
    "timestamp": "2026-06-24 15:04:56",
    "output_file": "outputVideos/ego_simple.mp4",
    "lanenet_model": "trained_models/LaneNetNew.pth",
    "lanenet_arch": "ENet",
    "hnet_model": "trained_models/hnet_best.pth",
    "video_file": "/Users/amannindra/Projects/Autonomous-Bicycle/HybridNets/demo/video/1.mp4",
    "width": 512,
    "height": 256,
    "embedding_activation": "raw",
    "hnet_poly_order": 3,
    "hnet_curve_thickness": 4,
    "delta_v": 0.5,
    "min_cluster_size": 50,
    "max_lanes": 3,
    "ego_alpha": 0.25,
    "ego_max_delta": 0.35,
    "ego_hold_decay": 0.85,
    "max_frames": 0
  },
  {
    "timestamp": "2026-06-24 15:05:01",
    "output_file": "outputVideos/ego_hold_decy_085.mp4",
    "lanenet_model": "trained_models/LaneNetNew.pth",
    "lanenet_arch": "ENet",
    "hnet_model": "trained_models/hnet_best.pth",
    "video_file": "/Users/amannindra/Projects/Autonomous-Bicycle/HybridNets/demo/video/1.mp4",
    "width": 512,
    "height": 256,
    "embedding_activation": "raw",
    "hnet_poly_order": 3,
    "hnet_curve_thickness": 4,
    "delta_v": 0.5,
    "min_cluster_size": 50,
    "max_lanes": 3,
    "ego_alpha": 0.25,
    "ego_max_delta": 0.35,
    "ego_hold_decay": 0.85,
    "max_frames": 0
  },
  {
    "timestamp": "2026-06-24 15:06:41",
    "output_file": "outputVideos/ego_no_max_line.mp4",
    "lanenet_model": "trained_models/LaneNetNew.pth",
    "lanenet_arch": "ENet",
    "hnet_model": "trained_models/hnet_best.pth",
    "video_file": "/Users/amannindra/Projects/Autonomous-Bicycle/HybridNets/demo/video/1.mp4",
    "width": 512,
    "height": 256,
    "embedding_activation": "raw",
    "hnet_poly_order": 3,
    "hnet_curve_thickness": 4,
    "delta_v": 0.5,
    "min_cluster_size": 50,
    "max_lanes": 10,
    "ego_alpha": 0.25,
    "ego_max_delta": 0.35,
    "ego_hold_decay": 0.85,
    "max_frames": 0
  },
  {
    "timestamp": "2026-06-24 15:15:45",
    "output_file": "outputVideos/ego_fix_matbe.mp4",
    "lanenet_model": "trained_models/LaneNetNew.pth",
    "lanenet_arch": "ENet",
    "hnet_model": "trained_models/hnet_best.pth",
    "video_file": "/Users/amannindra/Projects/Autonomous-Bicycle/HybridNets/demo/video/1.mp4",
    "width": 512,
    "height": 256,
    "embedding_activation": "sigmoid",
    "hnet_poly_order": 3,
    "hnet_curve_thickness": 4,
    "delta_v": 0.5,
    "min_cluster_size": 50,
    "max_lanes": 10,
    "ego_alpha": 0.25,
    "ego_max_delta": 0.35,
    "ego_hold_decay": 0.85,
    "max_frames": 0
  },
  {
    "timestamp": "2026-06-24 15:29:56",
    "output_file": "outputVideos/ego_f=embedding_activation_raw.mp4",
    "lanenet_model": "trained_models/LaneNetNew.pth",
    "lanenet_arch": "ENet",
    "hnet_model": "trained_models/hnet_best.pth",
    "video_file": "/Users/amannindra/Projects/Autonomous-Bicycle/HybridNets/demo/video/1.mp4",
    "width": 512,
    "height": 256,
    "embedding_activation": "raw",
    "hnet_poly_order": 3,
    "hnet_curve_thickness": 4,
    "delta_v": 0.5,
    "min_cluster_size": 50,
    "max_lanes": 10,
    "max_frames": 0
  },
  {
    "timestamp": "2026-06-24 15:32:35",
    "output_file": "outputVideos/ego_f=embedding_activation_sigmoid.mp4",
    "lanenet_model": "trained_models/LaneNetNew.pth",
    "lanenet_arch": "ENet",
    "hnet_model": "trained_models/hnet_best.pth",
    "video_file": "/Users/amannindra/Projects/Autonomous-Bicycle/HybridNets/demo/video/1.mp4",
    "width": 512,
    "height": 256,
    "embedding_activation": "sigmoid",
    "hnet_poly_order": 3,
    "hnet_curve_thickness": 4,
    "delta_v": 0.5,
    "min_cluster_size": 50,
    "max_lanes": 10,
    "max_frames": 0
  },
  {
    "timestamp": "2026-06-24 15:33:02",
    "output_file": "outputVideos/ego_f=embedding_activation_raw.mp4",
    "lanenet_model": "trained_models/LaneNetNew.pth",
    "lanenet_arch": "ENet",
    "hnet_model": "trained_models/hnet_best.pth",
    "video_file": "/Users/amannindra/Projects/Autonomous-Bicycle/HybridNets/demo/video/1.mp4",
    "width": 512,
    "height": 256,
    "embedding_activation": "raw",
    "hnet_poly_order": 3,
    "hnet_curve_thickness": 4,
    "delta_v": 0.5,
    "min_cluster_size": 50,
    "max_lanes": 10,
    "max_frames": 0
  },
  {
    "timestamp": "2026-06-24 15:42:06",
    "output_file": "outputVideos/output_hnet_original.mp4",
    "lanenet_model": "trained_models/LaneNetNew.pth",
    "lanenet_arch": "ENet",
    "hnet_model": "trained_models/hnet_best.pth",
    "video_file": "/Users/amannindra/Projects/Autonomous-Bicycle/HybridNets/demo/video/1.mp4",
    "width": 512,
    "height": 256,
    "embedding_activation": "raw",
    "hnet_poly_order": 3,
    "hnet_curve_thickness": 4,
    "delta_v": 0.5,
    "min_cluster_size": 50,
    "max_lanes": 10,
    "max_frames": 0
  },
  {
    "timestamp": "2026-06-24 15:43:17",
    "output_file": "outputVideos/output_hnet_original_sigmoid.mp4",
    "lanenet_model": "trained_models/LaneNetNew.pth",
    "lanenet_arch": "ENet",
    "hnet_model": "trained_models/hnet_best.pth",
    "video_file": "/Users/amannindra/Projects/Autonomous-Bicycle/HybridNets/demo/video/1.mp4",
    "width": 512,
    "height": 256,
    "embedding_activation": "sigmoid",
    "hnet_poly_order": 3,
    "hnet_curve_thickness": 4,
    "delta_v": 0.5,
    "min_cluster_size": 50,
    "max_lanes": 10,
    "max_frames": 0
  },
  {
    "timestamp": "2026-06-24 15:51:35",
    "output_file": "outputVideos/output_hnet_fixed.mp4",
    "lanenet_model": "trained_models/LaneNetNew.pth",
    "lanenet_arch": "ENet",
    "hnet_model": "trained_models/hnet_best.pth",
    "video_file": "/Users/amannindra/Projects/Autonomous-Bicycle/HybridNets/demo/video/1.mp4",
    "width": 512,
    "height": 256,
    "embedding_activation": "sigmoid",
    "hnet_poly_order": 3,
    "hnet_curve_thickness": 4,
    "delta_v": 0.5,
    "min_cluster_size": 50,
    "max_lanes": 10,
    "max_frames": 0
  },
  {
    "timestamp": "2026-06-24 15:53:10",
    "output_file": "outputVideos/output_hnet_fixed_raw.mp4",
    "lanenet_model": "trained_models/LaneNetNew.pth",
    "lanenet_arch": "ENet",
    "hnet_model": "trained_models/hnet_best.pth",
    "video_file": "/Users/amannindra/Projects/Autonomous-Bicycle/HybridNets/demo/video/1.mp4",
    "width": 512,
    "height": 256,
    "embedding_activation": "raw",
    "hnet_poly_order": 3,
    "hnet_curve_thickness": 4,
    "delta_v": 0.5,
    "min_cluster_size": 50,
    "max_lanes": 10,
    "max_frames": 0
  },
  {
    "timestamp": "2026-06-24 15:59:53",
    "output_file": "outputVideos/debug.mp4",
    "lanenet_model": "trained_models/LaneNetNew.pth",
    "lanenet_arch": "ENet",
    "hnet_model": "trained_models/hnet_best.pth",
    "video_file": "/Users/amannindra/Projects/Autonomous-Bicycle/HybridNets/demo/video/1.mp4",
    "width": 512,
    "height": 256,
    "embedding_activation": "sigmoid",
    "hnet_poly_order": 3,
    "hnet_curve_thickness": 4,
    "delta_v": 0.5,
    "min_cluster_size": 50,
    "max_lanes": 10,
    "max_frames": 0
  },
  {
    "timestamp": "2026-06-24 16:04:46",
    "output_file": "outputVideos/debug.mp4",
    "lanenet_model": "trained_models/epoch_030_train_16.pth",
    "lanenet_arch": "ENet",
    "hnet_model": "trained_models/hnet_best.pth",
    "video_file": "/Users/amannindra/Projects/Autonomous-Bicycle/HybridNets/demo/video/1.mp4",
    "width": 512,
    "height": 256,
    "embedding_activation": "sigmoid",
    "hnet_poly_order": 3,
    "hnet_curve_thickness": 4,
    "delta_v": 0.5,
    "min_cluster_size": 50,
    "max_lanes": 10,
    "max_frames": 0
  },
  {
    "timestamp": "2026-06-24 16:07:07",
    "output_file": "outputVideos/debug_sigmoid_epoche030.mp4",
    "lanenet_model": "trained_models/epoch_030_train_16.pth",
    "lanenet_arch": "ENet",
    "hnet_model": "trained_models/hnet_best.pth",
    "video_file": "/Users/amannindra/Projects/Autonomous-Bicycle/HybridNets/demo/video/1.mp4",
    "width": 512,
    "height": 256,
    "embedding_activation": "sigmoid",
    "hnet_poly_order": 3,
    "hnet_curve_thickness": 4,
    "delta_v": 0.5,
    "min_cluster_size": 50,
    "max_lanes": 10,
    "max_frames": 0
  },
  {
    "timestamp": "2026-06-24 16:07:09",
    "output_file": "outputVideos/debug_raw_epoche030.mp4",
    "lanenet_model": "trained_models/epoch_030_train_16.pth",
    "lanenet_arch": "ENet",
    "hnet_model": "trained_models/hnet_best.pth",
    "video_file": "/Users/amannindra/Projects/Autonomous-Bicycle/HybridNets/demo/video/1.mp4",
    "width": 512,
    "height": 256,
    "embedding_activation": "raw",
    "hnet_poly_order": 3,
    "hnet_curve_thickness": 4,
    "delta_v": 0.5,
    "min_cluster_size": 50,
    "max_lanes": 10,
    "max_frames": 0
  },
  {
    "timestamp": "2026-06-24 16:13:23",
    "output_file": "outputVideos/debug_sigmoid_epoche030.mp4",
    "lanenet_model": "trained_models/epoch_030_train_16.pth",
    "lanenet_arch": "ENet",
    "hnet_model": "trained_models/hnet_best.pth",
    "video_file": "/Users/amannindra/Projects/Autonomous-Bicycle/HybridNets/demo/video/1.mp4",
    "width": 512,
    "height": 256,
    "embedding_activation": "sigmoid",
    "hnet_poly_order": 3,
    "hnet_curve_thickness": 4,
    "delta_v": 0.5,
    "min_cluster_size": 50,
    "max_lanes": 10,
    "max_frames": 0
  },
  {
    "timestamp": "2026-06-24 16:13:24",
    "output_file": "outputVideos/debug_raw_epoche030.mp4",
    "lanenet_model": "trained_models/epoch_030_train_16.pth",
    "lanenet_arch": "ENet",
    "hnet_model": "trained_models/hnet_best.pth",
    "video_file": "/Users/amannindra/Projects/Autonomous-Bicycle/HybridNets/demo/video/1.mp4",
    "width": 512,
    "height": 256,
    "embedding_activation": "raw",
    "hnet_poly_order": 3,
    "hnet_curve_thickness": 4,
    "delta_v": 0.5,
    "min_cluster_size": 50,
    "max_lanes": 10,
    "max_frames": 0
  },
  {
    "timestamp": "2026-06-24 16:28:16",
    "output_file": "outputVideos/no_hnet.mp4",
    "lanenet_model": "trained_models/LaneNetNew.pth",
    "lanenet_arch": "ENet",
    "hnet_model": "none",
    "video_file": "/Users/amannindra/Projects/Autonomous-Bicycle/HybridNets/demo/video/1.mp4",
    "width": 512,
    "height": 256,
    "embedding_activation": "sigmoid",
    "hnet_poly_order": 3,
    "hnet_curve_thickness": 4,
    "delta_v": 0.5,
    "min_cluster_size": 20,
    "max_lanes": 10,
    "max_frames": 0
  },
  {
    "timestamp": "2026-06-24 16:32:45",
    "output_file": "outputVideos/no_hnet.mp4",
    "lanenet_model": "trained_models/LaneNetNew.pth",
    "lanenet_arch": "ENet",
    "hnet_model": "none",
    "video_file": "/Users/amannindra/Projects/Autonomous-Bicycle/HybridNets/demo/video/1.mp4",
    "width": 512,
    "height": 256,
    "embedding_activation": "raw",
    "hnet_poly_order": 3,
    "hnet_curve_thickness": 4,
    "delta_v": 0.5,
    "min_cluster_size": 20,
    "max_lanes": 10,
    "max_frames": 0
  },
  {
    "timestamp": "2026-06-25 14:30:09",
    "output_file": "outputVideos/debug_raw_epoche030.mp4",
    "lanenet_model": "trained_models/LaneNewTrained.pth",
    "lanenet_arch": "ENet",
    "hnet_model": "trained_models/hnet_best.pth",
    "video_file": "/Users/amannindra/Projects/Autonomous-Bicycle/HybridNets/demo/video/1.mp4",
    "width": 512,
    "height": 256,
    "embedding_activation": "raw",
    "hnet_poly_order": 3,
    "hnet_curve_thickness": 4,
    "delta_v": 0.5,
    "min_cluster_size": 50,
    "max_lanes": 10,
    "max_frames": 0
  },
  {
    "timestamp": "2026-06-25 14:36:08",
    "output_file": "outputVideos/debug_raw_epoche030.mp4",
    "lanenet_model": "trained_models/LaneNewTrained.pth",
    "lanenet_arch": "ENet",
    "hnet_model": "trained_models/hnet_best.pth",
    "video_file": "/Users/amannindra/Projects/Autonomous-Bicycle/HybridNets/demo/video/1.mp4",
    "width": 512,
    "height": 256,
    "embedding_activation": "raw",
    "hnet_poly_order": 3,
    "hnet_curve_thickness": 4,
    "delta_v": 0.5,
    "min_cluster_size": 50,
    "max_lanes": 10,
    "max_frames": 0
  },
  {
    "timestamp": "2026-06-25 14:37:33",
    "output_file": "outputVideos/debug_raw_epoche030.mp4",
    "lanenet_model": "trained_models/LaneNewTrained.pth",
    "lanenet_arch": "ENet",
    "hnet_model": "trained_models/hnet_best.pth",
    "video_file": "/Users/amannindra/Projects/Autonomous-Bicycle/HybridNets/demo/video/1.mp4",
    "width": 512,
    "height": 256,
    "embedding_activation": "raw",
    "hnet_poly_order": 3,
    "hnet_curve_thickness": 4,
    "delta_v": 0.5,
    "min_cluster_size": 50,
    "max_lanes": 10,
    "max_frames": 0
  },
  {
    "timestamp": "2026-06-25 14:51:41",
    "output_file": "outputVideos/debug_raw_epoche030.mp4",
    "lanenet_model": "trained_models/LaneNewTrained.pth",
    "lanenet_arch": "ENet",
    "hnet_model": "trained_models/hnet_best.pth",
    "video_file": "/Users/amannindra/Projects/Autonomous-Bicycle/HybridNets/demo/video/1.mp4",
    "width": 512,
    "height": 256,
    "embedding_activation": "raw",
    "hnet_poly_order": 3,
    "hnet_curve_thickness": 4,
    "delta_v": 0.5,
    "min_cluster_size": 50,
    "max_lanes": 10,
    "max_frames": 0
  },
  {
    "timestamp": "2026-06-25 15:02:33",
    "output_file": "outputVideos/debug_raw_epoche030.mp4",
    "lanenet_model": "trained_models/LaneNewTrained.pth",
    "lanenet_arch": "ENet",
    "hnet_model": "trained_models/hnet_best.pth",
    "video_file": "/Users/amannindra/Projects/Autonomous-Bicycle/HybridNets/demo/video/1.mp4",
    "width": 512,
    "height": 256,
    "embedding_activation": "raw",
    "hnet_poly_order": 3,
    "hnet_curve_thickness": 4,
    "delta_v": 0.5,
    "min_cluster_size": 50,
    "max_lanes": 10,
    "max_frames": 0
  },
  {
    "timestamp": "2026-06-25 15:31:14",
    "output_file": "outputVideos/debug_raw_epoche030.mp4",
    "lanenet_model": "trained_models/LaneNewTrained.pth",
    "lanenet_arch": "ENet",
    "hnet_model": "trained_models/hnet_best.pth",
    "video_file": "/Users/amannindra/Projects/Autonomous-Bicycle/HybridNets/demo/video/1.mp4",
    "width": 512,
    "height": 256,
    "embedding_activation": "raw",
    "hnet_poly_order": 3,
    "hnet_curve_thickness": 4,
    "delta_v": 0.5,
    "min_cluster_size": 50,
    "max_lanes": 10,
    "max_frames": 0
  },
  {
    "timestamp": "2026-06-25 15:53:11",
    "output_file": "outputVideos/debug_raw_epoche030.mp4",
    "lanenet_model": "trained_models/LaneNewTrained.pth",
    "lanenet_arch": "ENet",
    "hnet_model": "none",
    "video_file": "/Users/amannindra/Projects/Autonomous-Bicycle/HybridNets/demo/video/1.mp4",
    "width": 512,
    "height": 256,
    "embedding_activation": "raw",
    "hnet_poly_order": 3,
    "hnet_curve_thickness": 4,
    "delta_v": 0.5,
    "min_cluster_size": 50,
    "max_lanes": 10,
    "max_frames": 0
  }
]